{"id":"77215006","premium":false,"billing_type":{"id":"standard","name":"Стандарт"},"relations":[],"name":"Scala Data Engineer","insider_interview":{"id":"31119","url":"https://hh.ru/interview/31119?employerId=3127"},"response_letter_required":false,"area":{"id":"1","name":"Москва","url":"https://api.hh.ru/areas/1?host=hh.ru"},"salary":null,"type":{"id":"open","name":"Открытая"},"address":null,"allow_messages":true,"experience":{"id":"between3And6","name":"От 3 до 6 лет"},"schedule":{"id":"remote","name":"Удаленная работа"},"employment":{"id":"full","name":"Полная занятость"},"department":{"id":"mgfn-3127-it","name":"МегаФон, IT"},"contacts":null,"description":"<p>Мы разрабатываем облачную платформу конфиденциального машинного обучения и высоконагруженные сервисы данных, создающие конкурентное преимущество для бизнеса в области финтеха. Нашими продуктами пользуются 80% банковского сектора России.</p> <p>Мы ищем разработчика на Scala или Java, желающего перейти к разработке на Scala в области Big Data для участия в создании облачной платформы машинного обучения.</p> <p> </p> <p><strong>Чем предстоит заниматься:</strong></p> <p>• Разрабатывать MLOps/autoML платформы;<br />• Проектировать структуры хранения и представления данных;<br />• Разрабатывать промышленные сервисы распределенной обработки данных для поставки данных на платформу машинного обучения;<br />• Анализировать производительность и масштабировать продукты под возрастающую нагрузку;<br />• Писать юнит и интеграционные тесты, проводить code review.</p> <p> </p> <p><strong>Для решения этих задач требуется</strong></p> <p>• Опыт разработки на Scala / Java от 3 лет;<br />• Опыт работы со Spark от 1 года;<br />• Понимание принципов оптимизации обработки данных (знание форматов хранения данных, понимание принципов работы join и т.д.);<br />• Понимание архитектуры и принципов работы Spark-приложений;<br />• Навык работы с Docker, Kubernetes;</p> <p><strong>Будет плюсом:</strong></p> <p>• Опыт работы со SparkML;<br />• Опыт проектирования или работы с современными MLOps платформами;<br />• Понимание принципов обучения ML-моделей;<br />• Знание Python;<br />• Опыт работы с аналитическими базами данных Cassandra, Scylla etc.</p> <p><strong>Готовы сделать предоффер за 2 дня</strong></p> <p> </p> <p><strong>Что мы предлагаем:</strong><br />• Гибридный или удалённый формат работы c территории РФ;<br />• ДМС со стоматологией;<br />• Компенсация мобильной связи;<br />• Маркетплейс льгот и сервисов Mega4You;<br />• Понятный карьерный маршрут;<br />• 1 500 учебных про­грамм в мобильном приложении МегаФон Драйв;<br />• Программа поддержки и помощи сотрудникам;<br />• Активное корпора­тивное сообщество и насыщенный календарь событий.</p>","branded_description":null,"vacancy_constructor_template":null,"key_skills":[{"name":"SCALA"},{"name":"Spark"},{"name":"Java"}],"accept_handicapped":false,"accept_kids":false,"archived":false,"response_url":null,"specializations":[],"professional_roles":[{"id":"96","name":"Программист, разработчик"}],"code":null,"hidden":false,"quick_responses_allowed":false,"driver_license_types":[],"accept_incomplete_resumes":false,"employer":{"id":"3127","name":"МегаФон","url":"https://api.hh.ru/employers/3127?host=hh.ru","alternate_url":"https://hh.ru/employer/3127","logo_urls":{"90":"https://hhcdn.ru/employer-logo/3747371.png","240":"https://hhcdn.ru/employer-logo/3747372.png","original":"https://hhcdn.ru/employer-logo-original/826622.png"},"vacancies_url":"https://api.hh.ru/vacancies?employer_id=3127&host=hh.ru","trusted":true},"published_at":"2023-03-20T17:17:07+0300","created_at":"2023-03-20T17:17:07+0300","initial_created_at":"2023-02-20T13:26:15+0300","negotiations_url":null,"suitable_resumes_url":null,"apply_alternate_url":"https://hh.ru/applicant/vacancy_response?vacancyId=77215006","has_test":false,"test":null,"alternate_url":"https://hh.ru/vacancy/77215006","working_days":[],"working_time_intervals":[],"working_time_modes":[],"accept_temporary":false,"languages":[]}