{"id":"77614991","premium":false,"billing_type":{"id":"standard","name":"Стандарт"},"relations":[],"name":"Разработчик ETL","insider_interview":null,"response_letter_required":false,"area":{"id":"1","name":"Москва","url":"https://api.hh.ru/areas/1?host=hh.ru"},"salary":{"from":null,"to":230000,"currency":"RUR","gross":true},"type":{"id":"open","name":"Открытая"},"address":{"city":"Москва","street":"1-й Красногвардейский проезд","building":"21с1","lat":55.750028,"lng":37.534406,"description":null,"raw":"Москва, 1-й Красногвардейский проезд, 21с1","metro":null,"metro_stations":[]},"allow_messages":true,"experience":{"id":"between1And3","name":"От 1 года до 3 лет"},"schedule":{"id":"fullDay","name":"Полный день"},"employment":{"id":"full","name":"Полная занятость"},"department":null,"contacts":null,"description":"<p>В один из департаментов Комплекса экономической политики и имущественно-земельных отношений города Москвы требуется Разработчик ETL</p> <p><strong>Обязанности</strong></p> <ul> <li>Разработка/мониторинг/оптимизация ETL-процессов между внутренними и внешними сервисами</li> <li>Проектирование и оптимизация хранилища данных, витрин данных</li> <li>Разработка и поддержка пользовательских отчетов в BI-системе</li> <li>Разработка и постановка задач</li> <li>Написание сопроводительной документации: функциональных требований и инструкций</li> <li>Применение гибких методологий разработки (Scrum, Agile и т.д.)</li> </ul> <p><strong>Требования</strong></p> <ul> <li>Высшее образование</li> <li>Опыт работы с одной из СУБД (MSSQL, PostgreSQL)</li> <li>Уверенное знание SQL, анализ и оптимизация запросов</li> <li>Опыт ETL-разработки, знание Pentaho DI или аналога</li> <li>Навыки программирования: написание скриптов для работы с источниками и хранилищами данных, обработка данных</li> <li>Понимание принципов интеграции систем, построения хранилищ данных и управления качеством данных</li> <li>Умение работать с API, структурами XML и JSON</li> <li>Знание принципов безопасного поведения на рабочем месте, знание ФЗ № 149-ФЗ «Об информации, информационных технологиях и о защите информации», № 152-ФЗ &quot;О персональных данных&quot;</li> </ul> <p><strong>Условия</strong></p> <ul> <li>Официальное трудоустройство в подведомственное учреждение Правительства Москвы</li> <li>Доход обсуждается по результатам собеседования с успешным кандидатом</li> <li>Возможность карьерного и профессионального роста в рамках Комплекса экономической политики и имущественно-земельных отношений города Москвы</li> <li>Внутреннее корпоративное обучение</li> <li>Корпоративный спорт (хоккей, футбол, волейбол, настольный теннис и др.)</li> <li>Скидка на программы ДМС для Вас и ваших близких</li> <li>Обучение со скидкой в Skyeng, МИРБИС, Нетология, GeekBrains, SkillBox и т.д.</li> <li>Скидки партнеров (New Balance, СССР, Pilates class, X-fit, World Class и т.д.)</li> </ul> <p>Мы благодарим Вас за проявленный интерес к нашей вакансии. Ваше резюме будет рассмотрено в течение 14 дней. Если Ваш опыт работы и квалификация соответствуют требованиям к вакансии, мы с Вами свяжемся.</p>","branded_description":null,"vacancy_constructor_template":null,"key_skills":[{"name":"PostgreSQL"},{"name":"SQL"},{"name":"XML"},{"name":"MS SQL"},{"name":"ETL"}],"accept_handicapped":false,"accept_kids":false,"archived":false,"response_url":null,"specializations":[],"professional_roles":[{"id":"96","name":"Программист, разработчик"}],"code":null,"hidden":false,"quick_responses_allowed":false,"driver_license_types":[],"accept_incomplete_resumes":false,"employer":{"id":"4561908","name":"Центр развития Среда возможностей","url":"https://api.hh.ru/employers/4561908?host=hh.ru","alternate_url":"https://hh.ru/employer/4561908","logo_urls":{"90":"https://hhcdn.ru/employer-logo/3391389.png","240":"https://hhcdn.ru/employer-logo/3391390.png","original":"https://hhcdn.ru/employer-logo-original/737603.png"},"vacancies_url":"https://api.hh.ru/vacancies?employer_id=4561908&host=hh.ru","trusted":true},"published_at":"2023-03-02T17:24:54+0300","created_at":"2023-03-02T17:24:54+0300","initial_created_at":"2023-03-02T17:24:54+0300","negotiations_url":null,"suitable_resumes_url":null,"apply_alternate_url":"https://hh.ru/applicant/vacancy_response?vacancyId=77614991","has_test":false,"test":null,"alternate_url":"https://hh.ru/vacancy/77614991","working_days":[],"working_time_intervals":[],"working_time_modes":[],"accept_temporary":false,"languages":[]}