{"id":"77647224","premium":false,"billing_type":{"id":"standard","name":"Стандарт"},"relations":[],"name":"Senior Data engineer","insider_interview":null,"response_letter_required":false,"area":{"id":"1","name":"Москва","url":"https://api.hh.ru/areas/1?host=hh.ru"},"salary":{"from":null,"to":350000,"currency":"RUR","gross":true},"type":{"id":"open","name":"Открытая"},"address":null,"allow_messages":true,"experience":{"id":"between3And6","name":"От 3 до 6 лет"},"schedule":{"id":"remote","name":"Удаленная работа"},"employment":{"id":"full","name":"Полная занятость"},"department":null,"contacts":null,"description":"<p>Мы российская быстрорастущая платформа, созданная для взаимодействия разработчиков из России и ведущих компаний России, Европы и Америки.<br />Сейчас мы в поиске <strong>Data Engineer (DWH 3.0)</strong> на новый банковский проект</p> <p><strong>Одно из наших преимуществ </strong>- это оперативный процесс найма. Обычно 1-2 собеседования независимо от компании. А также большой пул проектов.</p> <strong>Обязанности:</strong> <p>—Профилирование/Понимание данных в системах источниках;</p> <p>—Разработка ETL/ELT;</p> <p>—Разработка слоев данных DWH, витрин DM;</p> <p>—Описание разработок в Confluence;</p> <p>—Оформление работ в Jira;</p> <p>—Участие в выборе технологий, компонентов, архитектуры решений;</p> <p>—Внедрение реализованных решений;</p> <strong>Требования:</strong> <p>— Уверенные навыки работы с одной современной СУБД (GreenPlum, PostgreSQL, MS SQL Server, Oracle, Teradata, и т.д.);</p> <p>— Хорошее знание SQL, опыт написания и оптимизации SQL запросов, процедур, представлений;</p> <p>— Опыт разработки и сопровождения ETL процессов;</p> <p>— Опыт разработки и внедрения корпоративных хранилищ данных (DWH);</p> <p>— Опытом развития решений в банковских АБС, желающих развиваться в области хранилищ данных (DWH);</p> <p>— Желателен опыт работы в банковской сфере;</p> <p><strong>Условия:</strong></p> <ul> <li> <p>удалённая работа с первого дня;</p> </li> <li>карьерный рост;</li> <li>job offer, отталкиваясь от ваших финансовых пожеланий;</li> <li>оформление по ТК РФ</li> </ul>","branded_description":null,"vacancy_constructor_template":null,"key_skills":[{"name":"DWH"},{"name":"ETL"},{"name":"ORACLE"},{"name":"MPP"},{"name":"MS SQL"},{"name":"PostgreSQL"}],"accept_handicapped":false,"accept_kids":false,"archived":false,"response_url":null,"specializations":[],"professional_roles":[{"id":"96","name":"Программист, разработчик"}],"code":null,"hidden":false,"quick_responses_allowed":false,"driver_license_types":[],"accept_incomplete_resumes":false,"employer":{"id":"5382804","name":"Volna.tech","url":"https://api.hh.ru/employers/5382804?host=hh.ru","alternate_url":"https://hh.ru/employer/5382804","logo_urls":{"original":"https://hhcdn.ru/employer-logo-original/917958.jpg","90":"https://hhcdn.ru/employer-logo/4112412.jpeg","240":"https://hhcdn.ru/employer-logo/4112413.jpeg"},"vacancies_url":"https://api.hh.ru/vacancies?employer_id=5382804&host=hh.ru","trusted":true},"published_at":"2023-03-03T13:33:34+0300","created_at":"2023-03-03T13:33:34+0300","initial_created_at":"2023-03-03T13:33:34+0300","negotiations_url":null,"suitable_resumes_url":null,"apply_alternate_url":"https://hh.ru/applicant/vacancy_response?vacancyId=77647224","has_test":false,"test":null,"alternate_url":"https://hh.ru/vacancy/77647224","working_days":[],"working_time_intervals":[],"working_time_modes":[],"accept_temporary":false,"languages":[]}